<signed-data>
    <data>
        <license>
            <licensor>Orbeon, Inc.</licensor>
            <licensee>Ando Randriamaro Tsihoarana</licensee>
            <organization>Université de la Réunion</organization>
            <email>andoratsi@gmail.com</email>
            <issued>2019-01-15</issued>
            <version/>
            <expiration>2019-04-15</expiration>
            <subscription-start/>
            <subscription-end/>
            <license-id/>
            <license-description/>
        </license>
    </data>
    <signature>MC0CFQCStuvoWxc22WcL7Sp+Z2/aHFSEIgIUavDWx1XOIQslfUTl7uTmI5SwE/o=</signature>
</signed-data>